{
    "EN": {
        "heading": "Knowledge Center",
        "title": "Lube oil systems – API 614",
        "subtitle": "Explore our smooth operating lube systems",
        "content": "The lube oil systems are custom engineered to meet the industry lubrication needs. Manufactured and tested as per Aramco specification 32-SAMSS-013, API 614, API 611, API 610, API 618 as well as manufacturer’s standards.",
        "img": "https://www.sulzer.com/-/media/images/products/pumps/firewater-pumps/dsc_7570.ashx?mw=564&hash=37C0FC924276842EF748D52EB1349D4BFC52043C"
    },
    "TH": {
        "heading": "Knowledge Center",
        "title": "Lube oil systems – API 614",
        "subtitle": "Explore our smooth operating lube systems",
        "content": "The lube oil systems are custom engineered to meet the industry lubrication needs. Manufactured and tested as per Aramco specification 32-SAMSS-013, API 614, API 611, API 610, API 618 as well as manufacturer’s standards.",
        "img": "https://www.sulzer.com/-/media/images/products/pumps/firewater-pumps/dsc_7570.ashx?mw=564&hash=37C0FC924276842EF748D52EB1349D4BFC52043C"
    }
}